vkarious/__init__.py
vkarious/change_capture.py
vkarious/cli.py
vkarious/db.py
vkarious/migration/vkarious_1.sql
vkarious/migration/vkarious_2.sql
vkarious/sql/change_capture.sql
vkarious-0.1.0.dist-info/METADATA
vkarious-0.1.0.dist-info/WHEEL
vkarious-0.1.0.dist-info/entry_points.txt
vkarious-0.1.0.dist-info/licenses/LICENSE
vkarious-0.1.0.dist-info/RECORD
