Metadata-Version: 2.4
Name: vkarious
Version: 0.1.0
Summary: Tool to get snapshots of PostgreSQL databases.
Author-email: Aybars Badur <aybars.badur@gmail.com>
License: MIT License
License-File: LICENSE
Requires-Python: >=3.11
Requires-Dist: click>=8.1.7
Requires-Dist: psycopg[binary]>=3.1.18
